swelibx/__init__.py
swelibx/patch_utils.py
swelibx-0.1.0.dist-info/licenses/LICENSE
swelibx-0.1.0.dist-info/METADATA
swelibx-0.1.0.dist-info/WHEEL
swelibx-0.1.0.dist-info/top_level.txt
swelibx-0.1.0.dist-info/RECORD
